[
	{
		"__TYPE__": "SharedSliceContent",
		"variation": "default",
		"primary": {
			"about_img": {
				"origin": {
					"id": "main",
					"url": "https://images.unsplash.com/photo-1515378960530-7c0da6231fb1",
					"width": 5616,
					"height": 3744
				},
				"url": "https://images.unsplash.com/photo-1515378960530-7c0da6231fb1",
				"width": 5616,
				"height": 3744,
				"edit": {
					"zoom": 1,
					"crop": {
						"x": 0,
						"y": 0
					},
					"background": "transparent"
				},
				"credits": null,
				"alt": null,
				"__TYPE__": "ImageContent",
				"thumbnails": {}
			},
			"heading_icon": {
				"origin": {
					"id": "main",
					"url": "https://images.unsplash.com/photo-1499951360447-b19be8fe80f5",
					"width": 5848,
					"height": 3899
				},
				"url": "https://images.unsplash.com/photo-1499951360447-b19be8fe80f5",
				"width": 5848,
				"height": 3899,
				"edit": {
					"zoom": 1,
					"crop": {
						"x": 0,
						"y": 0
					},
					"background": "transparent"
				},
				"credits": null,
				"alt": null,
				"__TYPE__": "ImageContent",
				"thumbnails": {}
			},
			"heading": {
				"__TYPE__": "FieldContent",
				"value": "term",
				"type": "Text"
			},
			"description": {
				"__TYPE__": "FieldContent",
				"value": "barn",
				"type": "Text"
			},
			"lists": {
				"__TYPE__": "GroupContentType",
				"value": [
					{
						"__TYPE__": "GroupItemContent",
						"value": [
							[
								"list_item",
								{
									"__TYPE__": "FieldContent",
									"value": "stick",
									"type": "Text"
								}
							]
						]
					}
				]
			},
			"btn": {
				"__TYPE__": "GroupContentType",
				"value": [
					{
						"__TYPE__": "GroupItemContent",
						"value": [
							[
								"title",
								{
									"__TYPE__": "FieldContent",
									"value": "led",
									"type": "Text"
								}
							],
							[
								"url",
								{
									"__TYPE__": "LinkContent",
									"value": {
										"__TYPE__": "ExternalLink",
										"url": "https://prismic.io"
									}
								}
							],
							[
								"black_bg",
								{
									"__TYPE__": "BooleanContent",
									"value": false
								}
							]
						]
					}
				]
			},
			"direction": {
				"__TYPE__": "FieldContent",
				"value": "Left",
				"type": "Select"
			}
		},
		"items": []
	}
]